Metadata-Version: 2.1
Name: jsonizer
Version: 1.1.0
Summary: Library for parsing nested JSONs into predefined classes 🔨✨
Home-page: https://github.com/abionics/jsonizer
Author: Alex Ermolaev
Author-email: abionics.dev@gmail.com
License: MIT
Keywords: json class loader parser detector
Platform: UNKNOWN
Classifier: Intended Audience :: Developers
Classifier: License :: OSI Approved :: MIT License
Classifier: Operating System :: OS Independent
Classifier: Programming Language :: Python :: 3
Classifier: Programming Language :: Python :: 3.9
Classifier: Programming Language :: Python :: 3.10
Classifier: Programming Language :: Python :: 3.11
Classifier: Topic :: Software Development :: Libraries :: Python Modules
Classifier: Topic :: Text Processing
Classifier: Topic :: Text Processing :: General
License-File: LICENSE.txt
